{"cameraMode":{"drawMode":0,"name":"Shaded","section":"Shading Mode"},"sceneLighting":false,"audioPlay":false,"sceneViewState":{"m_AlwaysRefresh":false,"showFog":true,"showSkybox":false,"showFlares":true,"showImageEffects":true,"showParticleSystems":true,"showVisualEffectGraphs":true,"m_FxEnabled":true},"in2DMode":false,"pivot":{"x":713.0,"y":474.0,"z":0.0},"rotation":{"x":0.45596975088119509,"y":0.001672309939749539,"z":-0.0009555701399222016,"w":0.8901359438896179},"size":856.1804809570313,"orthographic":true}